LICENSE
lexed/__init__.py
lexed/__main__.py
lexed/app.py
lexed/config.py
lexed/console.py
lexed/const.py
lexed/line.py
lexed/meta.py
lexed/window.py
lexed-0.0.1.10.dist-info/LICENSE
lexed-0.0.1.10.dist-info/METADATA
lexed-0.0.1.10.dist-info/WHEEL
lexed-0.0.1.10.dist-info/entry_points.txt
lexed-0.0.1.10.dist-info/top_level.txt
lexed-0.0.1.10.dist-info/RECORD
