Metadata-Version: 2.1
Name: lexed
Version: 0.0.1.10
Summary: LexEd - console python editor
Home-page: http://lexycore.github.io/lexed
Author: Alexander Kovalev
Author-email: ak@alkov.pro
License: MIT
Download-URL: https://github.com/lexycore/lexed.git
Keywords: development,editor
Platform: UNKNOWN
Classifier: Development Status :: 5 - Production/Stable
Classifier: Environment :: Console
Classifier: Intended Audience :: Developers
Classifier: Topic :: Text Editors :: Integrated Development Environments (IDE)
Classifier: License :: OSI Approved :: MIT License
Classifier: Natural Language :: English
Classifier: Programming Language :: Python :: 3.6
